scaruffi/__init__.py
scaruffi/__main__.py
scaruffi/api.py
scaruffi/log.py
scaruffi/tests.py
scaruffi-0.0.3.dist-info/METADATA
scaruffi-0.0.3.dist-info/WHEEL
scaruffi-0.0.3.dist-info/entry_points.txt
scaruffi-0.0.3.dist-info/top_level.txt
scaruffi-0.0.3.dist-info/RECORD
