Metadata-Version: 2.1
Name: scaruffi
Version: 0.0.3
Summary: Get some data from scaruffi.com.
Home-page: https://github.com/Dece/Scaruffi
Author: dece
Author-email: shgck@pistache.land
License: MIT
Platform: UNKNOWN
Classifier: Environment :: Console
Classifier: License :: OSI Approved :: MIT License
Classifier: Programming Language :: Python :: 3
Classifier: Programming Language :: Python :: 3.7
Requires-Python: >=3.7
Requires-Dist: requests (~=2.24)
Requires-Dist: beautifulsoup4 (~=4.9)
Requires-Dist: html5lib (~=1.1)
